temporal_adjuster/__init__.py
temporal_adjuster/__main__.py
temporal_adjuster/temporal_adjuster.py
temporal_adjuster/temporal_adjuster.pyi
temporal_adjuster/common/__init__.py
temporal_adjuster/common/decorators/__init__.py
temporal_adjuster/common/decorators/sequence_processor.py
temporal_adjuster/common/decorators/sequence_processor.pyi
temporal_adjuster/common/enums/__init__.py
temporal_adjuster/common/enums/day_of_week.py
temporal_adjuster/common/enums/day_of_week.pyi
temporal_adjuster/common/exceptions/__init__.py
temporal_adjuster/common/exceptions/common.py
temporal_adjuster/common/exceptions/common.pyi
temporal_adjuster/common/types/__init__.py
temporal_adjuster/common/types/dates.py
temporal_adjuster/common/types/dates.pyi
temporal_adjuster/modules/__init__.py
temporal_adjuster/modules/business_day_operations.py
temporal_adjuster/modules/first_and_last_day_operations.py
temporal_adjuster/modules/weekday_operations.py
tests/__init__.py
tests/test_first_and_last_days.py
tests/test_performance.py
tests/test_sequenceable.py
tests/test_weekday_operations.py
temporal_adjuster-1.2.0.dist-info/AUTHORS.md
temporal_adjuster-1.2.0.dist-info/LICENSE.md
temporal_adjuster-1.2.0.dist-info/METADATA
temporal_adjuster-1.2.0.dist-info/WHEEL
temporal_adjuster-1.2.0.dist-info/top_level.txt
temporal_adjuster-1.2.0.dist-info/RECORD
