Metadata-Version: 2.1
Name: temporal_adjuster
Version: 1.2.0
Summary: Adjusters are a key tool for modifying temporal objects. They exist to externalize the process of adjustment, permitting different approaches, as per the strategy design pattern. Temporal Adjuster provides tools that help pinpoint very specific moments in time, without having to manually count days, weeks, or months.
Author-email: Gabriel Mitelman Tkacz <gmtkacz@proton.me>
Maintainer-email: Gabriel Mitelman Tkacz <gmtkacz@proton.me>
License: MIT License
Project-URL: Repository, https://github.com/gtkacz/temporal_adjusters_py.git
Project-URL: Issues, https://github.com/gtkacz/temporal_adjusters_py/issues
Keywords: date,time,datetime,adjuster,adjustment,temporal
Classifier: Development Status :: 5 - Production/Stable
Classifier: Intended Audience :: Developers
Classifier: License :: OSI Approved :: MIT License
Classifier: Programming Language :: Python :: 3
Classifier: Programming Language :: Python :: 3.3
Classifier: Programming Language :: Python :: 3.4
Classifier: Programming Language :: Python :: 3.5
Classifier: Programming Language :: Python :: 3.6
Classifier: Programming Language :: Python :: 3.7
Classifier: Programming Language :: Python :: 3.8
Classifier: Programming Language :: Python :: 3.9
Classifier: Programming Language :: Python :: 3.10
Classifier: Programming Language :: Python :: 3.11
Classifier: Programming Language :: Python :: 3.12
Classifier: Operating System :: OS Independent
Requires-Python: >=3.3
License-File: LICENSE.md
License-File: AUTHORS.md
Requires-Dist: numpy
Requires-Dist: python-dateutil
